pyramid_multildap/__init__.py
pyramid_multildap/tests.py
pyramid_multildap/scaffolds/__init__.py
pyramid_multildap/scaffolds/ldapauth/CHANGES.txt_tmpl
pyramid_multildap/scaffolds/ldapauth/MANIFEST.in_tmpl
pyramid_multildap/scaffolds/ldapauth/README.txt_tmpl
pyramid_multildap/scaffolds/ldapauth/development.ini_tmpl
pyramid_multildap/scaffolds/ldapauth/production.ini_tmpl
pyramid_multildap/scaffolds/ldapauth/setup.py_tmpl
pyramid_multildap/scaffolds/ldapauth/+package+/__init__.py_tmpl
pyramid_multildap/scaffolds/ldapauth/+package+/views.py_tmpl
pyramid_multildap/scaffolds/ldapauth/+package+/templates/login.pt_tmpl
pyramid_multildap-0.2a6.dist-info/LICENSE.txt
pyramid_multildap-0.2a6.dist-info/METADATA
pyramid_multildap-0.2a6.dist-info/WHEEL
pyramid_multildap-0.2a6.dist-info/entry_points.txt
pyramid_multildap-0.2a6.dist-info/top_level.txt
pyramid_multildap-0.2a6.dist-info/RECORD
