Metadata-Version: 2.1
Name: pyramid-multildap
Version: 0.2a6
Summary: pyramid_multildap
Home-page: https://github.com/lmctv/pyramid_multildap
Author: Chris McDonough, Lorenzo M. Catucci
Author-email: pylons-discuss@groups.google.com
License: BSD-derived (http://www.repoze.org/LICENSE.txt)
Keywords: web pyramid pylons ldap
Platform: UNKNOWN
Classifier: Programming Language :: Python
Classifier: Framework :: Pylons
Classifier: Programming Language :: Python :: 2.7
Classifier: Topic :: System :: Systems Administration :: Authentication/Directory :: LDAP
Classifier: License :: Repoze Public License
Requires-Dist: ldappool
Requires-Dist: pyramid (>=1.4)
Requires-Dist: python-ldap
Provides-Extra: docs
Requires-Dist: Sphinx ; extra == 'docs'
Provides-Extra: testing
Requires-Dist: coverage ; extra == 'testing'
Requires-Dist: nose ; extra == 'testing'
